platform_checks-0.2.0.data/scripts/check_container_present
platform_checks-0.2.0.data/scripts/check_http_200
platform_checks-0.2.0.data/scripts/check_software_version
platformchecks/__init__.py
platformchecks/exitcode.py
platformchecks/checks/__init__.py
platformchecks/checks/docker.py
platformchecks/checks/http.py
platformchecks/checks/software.py
platformchecks/checks/softwareversions/__init__.py
platformchecks/checks/softwareversions/hashicorp.py
platformchecks/config/__init__.py
platformchecks/config/config.py
platform_checks-0.2.0.dist-info/LICENSE
platform_checks-0.2.0.dist-info/METADATA
platform_checks-0.2.0.dist-info/WHEEL
platform_checks-0.2.0.dist-info/top_level.txt
platform_checks-0.2.0.dist-info/RECORD
