Metadata-Version: 2.1
Name: platform-checks
Version: 0.2.0
Summary: Platform checks NRPE / Nagios
Home-page: https://devcentral.nasqueron.org/source/platform-checks/
Author: Sébastien Santoro
Author-email: dereckson@espace-win.org
License: BSD-2-Clause
Project-URL: Bug Tracker, https://devcentral.nasqueron.org/tag/monitoring_and_reporting/
Classifier: Programming Language :: Python :: 3
Classifier: License :: OSI Approved :: BSD License
Classifier: Operating System :: OS Independent
Classifier: Environment :: Console
Classifier: Intended Audience :: System Administrators
Classifier: Topic :: System :: Monitoring
Requires-Python: >=3.6
License-File: LICENSE
Requires-Dist: PyYAML<7.0,>=3.12
Requires-Dist: requests<3.0,>=2.20
Requires-Dist: semver~=3.0.2
